pd_fred/__init__.py
pd_fred/config.py
pd_fred/data_fetcher.py
pd_fred/pd_calculator.py
pd_fred/tests/__init__.py
pd_fred/tests/test_data_fetcher.py
pd_fred/tests/test_pd_calculator.py
pd_fred-0.1.0.dist-info/LICENSE
pd_fred-0.1.0.dist-info/METADATA
pd_fred-0.1.0.dist-info/WHEEL
pd_fred-0.1.0.dist-info/top_level.txt
pd_fred-0.1.0.dist-info/RECORD
