Metadata-Version: 2.1
Name: pd-fred
Version: 0.1.0
Summary: Python package to calculate Probability of Default using FRED data.
Home-page: https://github.com/yourusername/pd_fred
Author: Your Name
Author-email: your.email@example.com
License: UNKNOWN
Platform: UNKNOWN
Classifier: Programming Language :: Python :: 3
Classifier: License :: OSI Approved :: MIT License
Classifier: Operating System :: OS Independent
Requires-Python: >=3.6
License-File: LICENSE
Requires-Dist: pandas>=1.0.0
Requires-Dist: numpy>=1.18.0
Requires-Dist: fredapi>=0.4
Requires-Dist: scipy>=1.5.0
